streamsx/__init__.py
streamsx/build.py
streamsx/ec.py
streamsx/rest.py
streamsx/rest_errors.py
streamsx/rest_primitives.py
streamsx/service.py
streamsx/st.py
streamsx/types.py
streamsx/typing.py
streamsx/.toolkit/com.ibm.streamsx.topology/CHANGELOG.md
streamsx/.toolkit/com.ibm.streamsx.topology/info.xml
streamsx/.toolkit/com.ibm.streamsx.topology/toolkit.xml
streamsx/.toolkit/com.ibm.streamsx.topology/bin/spl-python-extract.py
streamsx/.toolkit/com.ibm.streamsx.topology/com.ibm.streamsx.topology/namespace-info.spl
streamsx/.toolkit/com.ibm.streamsx.topology/com.ibm.streamsx.topology/types.spl
streamsx/.toolkit/com.ibm.streamsx.topology/com.ibm.streamsx.topology.file/namespace-info.spl
streamsx/.toolkit/com.ibm.streamsx.topology/com.ibm.streamsx.topology.file/DirectoryWatcher/DirectoryWatcher.xml
streamsx/.toolkit/com.ibm.streamsx.topology/com.ibm.streamsx.topology.file/TextFileReader/TextFileReader.xml
streamsx/.toolkit/com.ibm.streamsx.topology/com.ibm.streamsx.topology.functional.java/namespace-info.spl
streamsx/.toolkit/com.ibm.streamsx.topology/com.ibm.streamsx.topology.functional.java/Aggregate/Aggregate.xml
streamsx/.toolkit/com.ibm.streamsx.topology/com.ibm.streamsx.topology.functional.java/Aggregate/aggregate_16.gif
streamsx/.toolkit/com.ibm.streamsx.topology/com.ibm.streamsx.topology.functional.java/Aggregate/aggregate_32.gif
streamsx/.toolkit/com.ibm.streamsx.topology/com.ibm.streamsx.topology.functional.java/Filter/Filter.xml
streamsx/.toolkit/com.ibm.streamsx.topology/com.ibm.streamsx.topology.functional.java/Filter/filter_16.gif
streamsx/.toolkit/com.ibm.streamsx.topology/com.ibm.streamsx.topology.functional.java/Filter/filter_32.gif
streamsx/.toolkit/com.ibm.streamsx.topology/com.ibm.streamsx.topology.functional.java/FlatMap/FlatMap.xml
streamsx/.toolkit/com.ibm.streamsx.topology/com.ibm.streamsx.topology.functional.java/FlatMap/functor_16.gif
streamsx/.toolkit/com.ibm.streamsx.topology/com.ibm.streamsx.topology.functional.java/FlatMap/functor_32.gif
streamsx-2.1.0.dist-info/LICENSE.txt
streamsx-2.1.0.dist-info/METADATA
streamsx-2.1.0.dist-info/WHEEL
streamsx-2.1.0.dist-info/entry_points.txt
streamsx-2.1.0.dist-info/top_level.txt
streamsx-2.1.0.dist-info/RECORD
