Metadata-Version: 1.1
Name: streamsx
Version: 2.1.0
Summary: IBM Streams Python Support
Home-page: https://github.com/IBMStreams/pypi.streamsx
Author: IBM Streams @ github.com
Author-email: hegermar@de.ibm.com
License: Apache License - Version 2.0
Download-URL: https://github.com/IBMStreams/pypi.streamsx/tarball/2.1.0
Keywords: streams,ibmstreams,streaming,analytics,streaming-analytics
Platform: UNKNOWN
Classifier: Development Status :: 5 - Production/Stable
Classifier: License :: OSI Approved :: Apache Software License
Classifier: Programming Language :: Python :: 3
Classifier: Programming Language :: Python :: 3.5
Classifier: Programming Language :: Python :: 3.6
Classifier: Programming Language :: Python :: 3.7
